seam/__init__.py
seam/auth.py
seam/client.py
seam/constants.py
seam/exceptions.py
seam/models.py
seam/modules/action_attempts.py
seam/options.py
seam/pagination.py
seam/paginator.py
seam/parse_options.py
seam/routes/__init__.py
seam/routes/access_codes.py
seam/routes/access_codes_simulate.py
seam/routes/access_codes_unmanaged.py
seam/routes/access_grants.py
seam/routes/access_grants_unmanaged.py
seam/routes/access_methods.py
seam/routes/access_methods_unmanaged.py
seam/routes/acs.py
seam/routes/acs_access_groups.py
seam/routes/acs_credentials.py
seam/routes/acs_encoders.py
seam/routes/acs_encoders_simulate.py
seam/routes/acs_entrances.py
seam/routes/acs_systems.py
seam/routes/acs_users.py
seam/routes/action_attempts.py
seam/routes/client_sessions.py
seam/routes/connect_webviews.py
seam/routes/connected_accounts.py
seam/routes/customers.py
seam/routes/devices.py
seam/routes/devices_simulate.py
seam/routes/devices_unmanaged.py
seam/routes/events.py
seam/routes/instant_keys.py
seam/routes/locks.py
seam/routes/locks_simulate.py
seam/routes/models.py
seam/routes/noise_sensors.py
seam/routes/noise_sensors_noise_thresholds.py
seam/routes/noise_sensors_simulate.py
seam/routes/phones.py
seam/routes/phones_simulate.py
seam/routes/spaces.py
seam/routes/thermostats.py
seam/routes/thermostats_daily_programs.py
seam/routes/thermostats_schedules.py
seam/routes/thermostats_simulate.py
seam/routes/user_identities.py
seam/routes/user_identities_unmanaged.py
seam/routes/webhooks.py
seam/routes/workspaces.py
seam/seam.py
seam/seam_multi_workspace.py
seam/seam_webhook.py
seam/token.py
seam/utils/deep_attr_dict.py
seam-1.145.0.dist-info/LICENSE.txt
seam-1.145.0.dist-info/METADATA
seam-1.145.0.dist-info/WHEEL
seam-1.145.0.dist-info/RECORD
