Metadata-Version: 2.1
Name: seam
Version: 1.145.0
Summary: SDK for the Seam API written in Python.
Home-page: https://github.com/seamapi/python
License: MIT
Author: Seam Labs, Inc.
Author-email: engineering@getseam.com
Requires-Python: >=3.10.0,<4.0.0
Classifier: License :: OSI Approved :: MIT License
Classifier: Programming Language :: Python :: 3
Classifier: Programming Language :: Python :: 3.10
Classifier: Programming Language :: Python :: 3.11
Classifier: Programming Language :: Python :: 3.12
Requires-Dist: dataclasses-json (>=0.6.4,<0.7.0)
Requires-Dist: niquests (>=3.6.4,<4.0.0)
Requires-Dist: svix (>=1.24.0,<2.0.0)
Project-URL: Repository, https://github.com/seamapi/python
